tests/__init__.py
tests/test_videocheck.py
tests/videos/ko.mp4
tests/videos/ok.mp4
videocheck/__init__.py
videocheck/cli.py
videocheck/main.py
videocheck-0.1.2.dist-info/LICENSE
videocheck-0.1.2.dist-info/METADATA
videocheck-0.1.2.dist-info/WHEEL
videocheck-0.1.2.dist-info/entry_points.txt
videocheck-0.1.2.dist-info/top_level.txt
videocheck-0.1.2.dist-info/zip-safe
videocheck-0.1.2.dist-info/RECORD
