Metadata-Version: 2.1
Name: videocheck
Version: 0.1.2
Summary: Automated tool to check consistency of your video library.
Home-page: https://github.com/arnaudsm/videocheck
Author: Arnaud de Saint Meloir
Author-email: arnaud.desaintmeloir@gmail.com
License: MIT license
Keywords: videocheck
Platform: UNKNOWN
Requires-Python: >=3.5
Requires-Dist: Click (>=7.0)
Requires-Dist: pandas
Requires-Dist: tqdm
